projection/__init__.py
projection/default_projections.py
projection/exceptions.py
projection/logging_config.py
projection/processor.py
projection/registry.py
projection/utils.py
projection/base/__init__.py
projection/base/config.py
projection/base/grid.py
projection/base/interpolation.py
projection/base/registry.py
projection/base/strategy.py
projection/base/transform.py
projection/gnomonic/__init__.py
projection/gnomonic/config.py
projection/gnomonic/grid.py
projection/gnomonic/strategy.py
projection/gnomonic/transform.py
projection/mercator/__init__.py
projection/mercator/config.py
projection/mercator/grid.py
projection/mercator/strategy.py
projection/mercator/transform.py
spherical_projections/__init__.py
spherical_projections/default_projections.py
spherical_projections/exceptions.py
spherical_projections/logging_config.py
spherical_projections/processor.py
spherical_projections/registry.py
spherical_projections/utils.py
spherical_projections/base/__init__.py
spherical_projections/base/config.py
spherical_projections/base/grid.py
spherical_projections/base/interpolation.py
spherical_projections/base/registry.py
spherical_projections/base/strategy.py
spherical_projections/base/transform.py
spherical_projections/gnomonic/__init__.py
spherical_projections/gnomonic/config.py
spherical_projections/gnomonic/grid.py
spherical_projections/gnomonic/strategy.py
spherical_projections/gnomonic/transform.py
spherical_projections/mercator/__init__.py
spherical_projections/mercator/config.py
spherical_projections/mercator/grid.py
spherical_projections/mercator/strategy.py
spherical_projections/mercator/transform.py
spherical_projection-0.1.0b0.dist-info/METADATA
spherical_projection-0.1.0b0.dist-info/WHEEL
spherical_projection-0.1.0b0.dist-info/top_level.txt
spherical_projection-0.1.0b0.dist-info/RECORD
