Metadata-Version: 2.1
Name: spherical_projection
Version: 0.1.0b0
Summary: A spherical projection library for Python
Home-page: https://github.com/RobinsonGarcia/ProjectionRegistry/
Author: RLSGarcia
Author-email: RLSGarcia@icloud.com
Classifier: Programming Language :: Python :: 3
Classifier: Operating System :: OS Independent
Requires-Python: >=3.7
Requires-Dist: numpy >=1.20.0
Requires-Dist: pydantic >=1.10.0
Requires-Dist: scipy >=1.5.0
Requires-Dist: opencv-python >=4.5.0
